awaitable_tools/__init__.py
awaitable_tools/decorators.py
awaitable_tools/py.typed
awaitable_tools/types.py
awaitable_tools/utils.py
awaitable_tools-0.0.1.dist-info/licenses/LICENSE
awaitable_tools-0.0.1.dist-info/METADATA
awaitable_tools-0.0.1.dist-info/WHEEL
awaitable_tools-0.0.1.dist-info/top_level.txt
awaitable_tools-0.0.1.dist-info/RECORD
