Metadata-Version: 2.4
Name: awaitable-tools
Version: 0.0.1
Summary: Tools to bridge coroutines and non-coroutine awaitables in Python
Author-email: AlanBogarin <bogarin01alan@gmail.com>
License: MIT License
Project-URL: Homepage, https://github.com/AlanBogarin/awaitable-tools
Project-URL: Bug Tracker, https://github.com/AlanBogarin/awaitable-tools/issues
Keywords: async,python,awaitable,tools,AlanBogarin
Classifier: Programming Language :: Python :: 3
Classifier: Programming Language :: Python :: 3.8
Classifier: Programming Language :: Python :: 3.9
Classifier: Programming Language :: Python :: 3.10
Classifier: Programming Language :: Python :: 3.11
Classifier: Programming Language :: Python :: 3.12
Classifier: Programming Language :: Python :: 3.13
Classifier: Programming Language :: Python :: 3.14
Classifier: License :: OSI Approved :: MIT License
Classifier: Operating System :: OS Independent
Requires-Python: >=3.8
License-File: LICENSE
Requires-Dist: typing-extensions>=4.12.2
Dynamic: license-file
